markdown_external_link_finder/__init__.py
markdown_external_link_finder/__main__.py
markdown_external_link_finder/extract.py
markdown_external_link_finder/util.py
markdown_external_link_finder-0.0.1.dist-info/METADATA
markdown_external_link_finder-0.0.1.dist-info/WHEEL
markdown_external_link_finder-0.0.1.dist-info/top_level.txt
markdown_external_link_finder-0.0.1.dist-info/RECORD
